mapaction/__init__.py
mapaction/cli.py
mapaction/libs/__init__.py
mapaction/libs/version.py
mapaction/modules/templates/__init__.py
mapaction/modules/templates/templates.py
mapaction/scripts/mapElementLocationsPro.py
mapaction-0.1.9.dist-info/entry_points.txt
mapaction-0.1.9.dist-info/WHEEL
mapaction-0.1.9.dist-info/METADATA
mapaction-0.1.9.dist-info/RECORD
